lvmcache2mqtt/__init__.py
lvmcache2mqtt/__main__.py
lvmcache2mqtt/average_calculator.py
lvmcache2mqtt/collect.py
lvmcache2mqtt/config.py
lvmcache2mqtt-0.5.0.dist-info/LICENSE
lvmcache2mqtt-0.5.0.dist-info/METADATA
lvmcache2mqtt-0.5.0.dist-info/WHEEL
lvmcache2mqtt-0.5.0.dist-info/top_level.txt
lvmcache2mqtt-0.5.0.dist-info/RECORD
