Metadata-Version: 2.1
Name: lvmcache2mqtt
Version: 0.5.0
Summary: Python module to pulish LVM cache statistics to MQTT.
Home-page: https://github.com/JonasPed/lvmcache2mqtt
Author: Jonas Pedersen
Author-email: jonas@pedersen.ninja
License: Apache 2.0
Platform: UNKNOWN
Classifier: Programming Language :: Python :: 3
Classifier: License :: OSI Approved :: Apache Software License
Classifier: Operating System :: POSIX :: Linux
Requires-Python: >=3.6
